[
  {
    "index": 14159,
    "valueOfType": 8,
    "valueOfSubType": 0,
    "name": "",
    "options": [],
    "href": "https://www.sachianail.com/pitem/%3C%=%20ProductID%20%%3E"
  },
  {
    "index": 713,
    "valueOfType": 7,
    "valueOfSubType": 8,
    "name": "日式原木美甲工具磁吸托盤",
    "options": [
      { "name": "", "value": null },
      { "name": "A款方型原木磁性工具收納托盤", "value": 10594 }
    ],
    "href": "https://www.sachianail.com/pitem/M00000184"
  },
  {
    "index": 1253,
    "valueOfType": 8,
    "valueOfSubType": 1,
    "name": "超閃美甲水鑽鏈條",
    "options": [
      { "name": "", "value": null },
      { "name": "01 爪鑽鏈條-細鑽-銀", "value": 12686 },
      { "name": "02 爪鑽鏈條-中粗鑽-銀色25", "value": 12687 },
      { "name": "03 爪鑽鏈條-細珍珠-銀", "value": 12688 },
      { "name": "04 爪鑽鏈條-中粗珍珠-銀", "value": 12689 },
      { "name": "05 爪鑽鏈條AB彩鑽", "value": 12690 },
      { "name": "06爪鑽鏈條AB彩鑽粗", "value": 12691 },
      { "name": "6格爪鑽鏈1920-A款", "value": 12692 },
      { "name": "6格金屬鏈條1920-B款", "value": 12693 },
      { "name": "07 爪鑽鏈條-細鑽-金", "value": 12694 },
      { "name": "08 爪鑽鏈條-中粗+金", "value": 12695 },
      { "name": "09 爪鑽鏈條-細珍珠-金色25", "value": 12696 },
      { "name": "10 爪鑽鏈條細槍黑透明鑽", "value": 12697 },
      { "name": "11 爪鑽鏈條-細大紅鑽", "value": 12698 },
      { "name": "29號金底2mm珍珠", "value": 12699 },
      { "name": "30號金色4MM排鏈金(10公分)", "value": 12700 },
      { "name": "31號銀色4MM排鏈金(10公分)", "value": 12701 },
      { "name": "珍珠鏈條銀色底", "value": 12705 }
    ],
    "href": "https://www.sachianail.com/pitem/M00000441"
  }
]
